tkflu/__init__.py
tkflu/__main__.py
tkflu/badge.py
tkflu/button.py
tkflu/bwm.py
tkflu/checkbox.py
tkflu/constants.py
tkflu/customwindow.py
tkflu/customwindow2.py
tkflu/defs.py
tkflu/demos/__init__.py
tkflu/demos/acrylic1.py
tkflu/demos/demo.py
tkflu/demos/demo1.py
tkflu/demos/designer.py
tkflu/demos/grad.py
tkflu/demos/grad2.py
tkflu/demos/grad3.py
tkflu/demos/screenshot.py
tkflu/demos/scroll.py
tkflu/demos/test.py
tkflu/demos/tooltip.py
tkflu/designs/__init__.py
tkflu/designs/animation.py
tkflu/designs/badge.py
tkflu/designs/button.py
tkflu/designs/design.py
tkflu/designs/entry.py
tkflu/designs/fonts/__init__.py
tkflu/designs/fonts/segoe_fluent_icons.ttf
tkflu/designs/fonts/segoeui.ttf
tkflu/designs/frame.py
tkflu/designs/gradient.py
tkflu/designs/label.py
tkflu/designs/menubar.py
tkflu/designs/primary_color.py
tkflu/designs/renderer.py
tkflu/designs/scrollbar.py
tkflu/designs/slider.py
tkflu/designs/text.py
tkflu/designs/tooltip.py
tkflu/designs/window.py
tkflu/entry.py
tkflu/frame.py
tkflu/icons.py
tkflu/image.py
tkflu/label.py
tkflu/listbox.py
tkflu/litenav.py
tkflu/menu.py
tkflu/menubar.py
tkflu/popupmenu.py
tkflu/popupwindow.py
tkflu/scrollbar.py
tkflu/slider.py
tkflu/text.py
tkflu/thememanager.py
tkflu/togglebutton.py
tkflu/tooltip.py
tkflu/toplevel.py
tkflu/window.py
tkfluent-0.1.6.dist-info/METADATA
tkfluent-0.1.6.dist-info/WHEEL
tkfluent-0.1.6.dist-info/RECORD
