Metadata-Version: 2.3
Name: tkfluent
Version: 0.1.6
Summary: Fluent(SunValley) Design for Tkinter. Modern GUI
License: GPL-3.0
Keywords: tkfluent,tksvg,tkinter,fluent,modern,GUI,interface
Author: XiangQinxi
Author-email: xiangqinxi@outlook.com
Requires-Python: >=3.8,<4.0
Classifier: Development Status :: 4 - Beta
Classifier: Environment :: MacOS X
Classifier: Environment :: Win32 (MS Windows)
Classifier: Environment :: X11 Applications
Classifier: License :: OSI Approved :: GNU General Public License v3 (GPLv3)
Classifier: Natural Language :: Chinese (Simplified)
Classifier: Natural Language :: English
Classifier: Operating System :: MacOS
Classifier: Operating System :: Microsoft :: Windows
Classifier: Operating System :: POSIX :: Linux
Classifier: Programming Language :: Python :: 3
Classifier: Programming Language :: Python :: 3.8
Classifier: Programming Language :: Python :: 3.9
Classifier: Programming Language :: Python :: 3.10
Classifier: Programming Language :: Python :: 3.11
Classifier: Programming Language :: Python :: 3.12
Classifier: Programming Language :: Python :: 3.13
Classifier: Programming Language :: Tcl
Classifier: Topic :: Software Development :: Libraries :: Python Modules
Requires-Dist: easydict (>=1.13,<2.0)
Requires-Dist: numpy
Requires-Dist: pillow (>=10.2.0,<11.0.0)
Requires-Dist: svgwrite (>=1.4.3,<2.0.0)
Requires-Dist: tkdeft (==0.1.2)
Requires-Dist: tkextrafont (>=0.6.3,<0.7.0)
Requires-Dist: tksvg (>=0.7.4,<0.8.0)
Project-URL: Documentation, https://tkfluent.netlify.app
